pythoncolouringsmodsV2/__init__.py
pythoncolouringsmodsV2-1.0.2.dist-info/METADATA
pythoncolouringsmodsV2-1.0.2.dist-info/WHEEL
pythoncolouringsmodsV2-1.0.2.dist-info/top_level.txt
pythoncolouringsmodsV2-1.0.2.dist-info/RECORD
